mkdocs_random_walk_plugin/__init__.py
mkdocs_random_walk_plugin/plugin.py
mkdocs_random_walk_plugin/random_walk.js
mkdocs_random_walk_plugin-0.1.1.dist-info/LICENSE
mkdocs_random_walk_plugin-0.1.1.dist-info/METADATA
mkdocs_random_walk_plugin-0.1.1.dist-info/WHEEL
mkdocs_random_walk_plugin-0.1.1.dist-info/entry_points.txt
mkdocs_random_walk_plugin-0.1.1.dist-info/top_level.txt
mkdocs_random_walk_plugin-0.1.1.dist-info/RECORD
