Metadata-Version: 2.2
Name: mkdocs-random_walk-plugin
Version: 0.1.1
Summary: A MkDocs plugin that generates a random link of pages
Home-page: https://github.com/NoughtQ/mkdocs-random_walk-plugin
Author: NoughtQ
Author-email: noughtq666@gmail.com
License: MIT
Keywords: mkdocs python markdown notes random random_walk
Classifier: Development Status :: 3 - Alpha
Classifier: Intended Audience :: Developers
Classifier: Intended Audience :: Information Technology
Classifier: License :: OSI Approved :: MIT License
Classifier: Programming Language :: Python
Classifier: Programming Language :: Python :: 3.5
Classifier: Programming Language :: Python :: 3.6
Classifier: Programming Language :: Python :: 3.7
Classifier: Programming Language :: Python :: 3.8
Classifier: Programming Language :: Python :: 3.9
Classifier: Programming Language :: Python :: 3.10
Classifier: Programming Language :: Python :: 3.11
Classifier: Programming Language :: Python :: 3.12
Classifier: Programming Language :: Python :: 3.13
Requires-Python: >=3.5
License-File: LICENSE
Requires-Dist: mkdocs
Dynamic: author
Dynamic: author-email
Dynamic: classifier
Dynamic: description
Dynamic: description-content-type
Dynamic: home-page
Dynamic: keywords
Dynamic: license
Dynamic: requires-dist
Dynamic: requires-python
Dynamic: summary
